viridis/__init__.py
viridis/tree.py
viridis-0.4.2.dist-info/DESCRIPTION.rst
viridis-0.4.2.dist-info/METADATA
viridis-0.4.2.dist-info/RECORD
viridis-0.4.2.dist-info/WHEEL
viridis-0.4.2.dist-info/metadata.json
viridis-0.4.2.dist-info/top_level.txt
